{
  "SP_ArrowBack": {
    "id": "arrow_upward",
    "rotate": 270
  },
  "SP_ArrowDown": {
    "id": "arrow_upward",
    "rotate": 180
  },
  "SP_ArrowForward": {
    "id": "arrow_upward",
    "rotate": 90
  },
  "SP_ArrowLeft": {
    "id": "arrow_upward",
    "rotate": 270
  },
  "SP_ArrowRight": {
    "id": "arrow_upward",
    "rotate": 90
  },
  "SP_ArrowUp": {
    "id": "arrow_upward"
  },
  "SP_CommandLink": {
    "id": "east"
  },
  "SP_DialogDiscardButton": {
    "id": "delete"
  },
  "SP_FileDialogBack": {
    "id": "arrow_upward",
    "rotate": 270
  },
  "SP_FileDialogToParent": {
    "id": "arrow_upward"
  },
  "SP_MediaPlay": {
    "id": "play_arrow"
  },
  "SP_MediaPause": {
    "id": "pause"
  },
  "SP_MediaSeekForward": {
    "id": "fast_forward"
  },
  "SP_MediaSeekBackward": {
    "id": "fast_rewind"
  },
  "SP_MediaSkipBackward": {
    "id": "skip_previous"
  },
  "SP_MediaSkipForward": {
    "id": "skip_next"
  },
  "SP_MediaStop": {
    "id": "stop"
  },
  "SP_MediaVolume": {
    "id": "volume_up"
  },
  "SP_MediaVolumeMuted": {
    "id": "volume_mute"
  },
  "SP_TitleBarCloseButton": {
    "id": "close"
  },
  "SP_TitleBarNormalButton": {
    "id": "flip_to_front"
  },
  "SP_ToolBarHorizontalExtensionButton": {
    "id": "double_arrow"
  },
  "SP_ToolBarVerticalExtensionButton": {
    "id": "double_arrow",
    "rotate": 90
  }
}
